oxypy/__init__.py
oxypy/default.py
oxypy/either.py
oxypy/option.py
oxypy/panic.py
oxypy/py.typed
oxypy/result.py
oxypy/utils.py
oxypy-1.0.1.dist-info/LICENSE.txt
oxypy-1.0.1.dist-info/METADATA
oxypy-1.0.1.dist-info/WHEEL
oxypy-1.0.1.dist-info/top_level.txt
oxypy-1.0.1.dist-info/RECORD
