Metadata-Version: 2.1
Name: oxypy
Version: 1.0.1
Summary: Essential Rust Utilities in Python
Author: attr: oxypy.__author__
Author-email: rmorgan512@protonmail.ch
License: MIT
Platform: unix
Platform: linux
Platform: osx
Platform: cygwin
Platform: win32
Classifier: Development Status :: 4 - Beta
Classifier: Intended Audience :: Developers
Classifier: Programming Language :: Python :: 3
Classifier: Programming Language :: Python :: 3 :: Only
Classifier: Programming Language :: Python :: 3.8
Classifier: Programming Language :: Python :: 3.9
Classifier: Programming Language :: Python :: 3.10
Classifier: Programming Language :: Python :: 3.11
Requires-Python: >=3.8
License-File: LICENSE.txt
Provides-Extra: testing
Requires-Dist: tox ==4.6.0 ; extra == 'testing'
Requires-Dist: pytest ==7.3.1 ; extra == 'testing'
Requires-Dist: pytest-cov ==4.1.0 ; extra == 'testing'
Requires-Dist: mypy ==1.3.0 ; extra == 'testing'
